lenu/__init__.py
lenu/console.py
lenu/data/2023-09-28-elf-code-list-v1.5.csv
lenu/data/__init__.py
lenu/data/elf_codes.py
lenu/data/goldencopyfiles.py
lenu/data/lei.py
lenu/ml/__init__.py
lenu/ml/cnames.py
lenu/ml/eval.py
lenu/ml/features.py
lenu/ml/models.py
lenu/ml/pipelines.py
lenu/ml/test/__init__.py
lenu/ml/test/test_features.py
lenu/modelhub.py
lenu/util.py
lenu-0.3.1.dist-info/entry_points.txt
lenu-0.3.1.dist-info/LICENSE
lenu-0.3.1.dist-info/WHEEL
lenu-0.3.1.dist-info/METADATA
lenu-0.3.1.dist-info/RECORD
