Metadata-Version: 2.1
Name: lenu
Version: 0.3.1
Summary: Legal Entity Name Understanding
Author: aarimond
Author-email: alexander.arimond@sociovestix.com
Requires-Python: >=3.8,<3.10
Classifier: Programming Language :: Python :: 3
Classifier: Programming Language :: Python :: 3.8
Classifier: Programming Language :: Python :: 3.9
Requires-Dist: importlib-resources (>=5.7.1,<6.0.0)
Requires-Dist: pandas (>=1.4.2,<2.0.0)
Requires-Dist: pydantic (>=1.9.0,<2.0.0)
Requires-Dist: requests (>=2.27.1,<3.0.0)
Requires-Dist: scikit-learn (>=1.0.2,<2.0.0)
Requires-Dist: torch (>=1.13.1,<2.0.0)
Requires-Dist: transformers (>=4.26.0,<5.0.0)
Requires-Dist: typer[all] (>=0.4.1,<0.5.0)
Requires-Dist: types-requests (>=2.27.16,<3.0.0)
